picasso/CloneTree.py
picasso/__init__.py
picasso/build_tree.py
picasso/itol_utils.py
picasso/py.typed
picasso/utils.py
picasso/sample_data/cnas.txt
picasso_phylo-0.1.2.dist-info/licenses/LICENSE
picasso_phylo-0.1.2.dist-info/METADATA
picasso_phylo-0.1.2.dist-info/WHEEL
picasso_phylo-0.1.2.dist-info/top_level.txt
picasso_phylo-0.1.2.dist-info/RECORD
