Metadata-Version: 2.4
Name: picasso_phylo
Version: 0.1.2
Summary: Phylogenetic Inference of Copy number Alterations in Single-cell Sequencing data Optimization
Author-email: Sitara Persad <sitara.persad@columbia.edu>
Maintainer-email: Sitara Persad <sitara.persad@columbia.edu>
License: MIT
Project-URL: Homepage, https://github.com/sitarapersad/picasso_phylo
Project-URL: Documentation, https://picasso-phylo.readthedocs.io/
Project-URL: Repository, https://github.com/sitarapersad/picasso_phylo.git
Project-URL: Bug Tracker, https://github.com/sitarapersad/picasso_phylo/issues
Project-URL: Changelog, https://github.com/sitarapersad/picasso_phylo/blob/main/CHANGELOG.md
Keywords: phylogenetics,single-cell,genomics,copy-number-alterations,cancer,tumor-evolution,scRNA-seq
Classifier: Development Status :: 4 - Beta
Classifier: Intended Audience :: Science/Research
Classifier: License :: OSI Approved :: MIT License
Classifier: Operating System :: OS Independent
Classifier: Programming Language :: Python :: 3
Classifier: Programming Language :: Python :: 3.10
Classifier: Programming Language :: Python :: 3.11
Classifier: Programming Language :: Python :: 3.12
Classifier: Topic :: Scientific/Engineering :: Bio-Informatics
Classifier: Topic :: Scientific/Engineering :: Medical Science Apps.
Classifier: Typing :: Typed
Requires-Python: >=3.10
License-File: LICENSE
Requires-Dist: numpy>=1.24.0
Requires-Dist: pandas>=2.0.0
Requires-Dist: pomegranate>=1.0.4
Requires-Dist: ete3>=3.1.3
Requires-Dist: matplotlib>=3.6.0
Requires-Dist: seaborn>=0.12.0
Requires-Dist: tqdm>=4.64.0
Requires-Dist: scipy>=1.10.0
Provides-Extra: dev
Requires-Dist: pytest>=7.0.0; extra == "dev"
Requires-Dist: pytest-cov>=4.0.0; extra == "dev"
Requires-Dist: black>=22.0.0; extra == "dev"
Requires-Dist: isort>=5.0.0; extra == "dev"
Requires-Dist: flake8>=5.0.0; extra == "dev"
Requires-Dist: mypy>=1.0.0; extra == "dev"
Requires-Dist: pre-commit>=2.0.0; extra == "dev"
Provides-Extra: docs
Requires-Dist: sphinx>=5.0.0; extra == "docs"
Requires-Dist: sphinx-rtd-theme>=1.0.0; extra == "docs"
Requires-Dist: sphinx-autodoc-typehints>=1.0.0; extra == "docs"
Requires-Dist: numpydoc>=1.5.0; extra == "docs"
Provides-Extra: jupyter
Requires-Dist: jupyter>=1.0.0; extra == "jupyter"
Requires-Dist: ipykernel>=6.0.0; extra == "jupyter"
Requires-Dist: notebook>=6.0.0; extra == "jupyter"
Provides-Extra: viz
Requires-Dist: pyqt5>=5.15.0; extra == "viz"
Dynamic: license-file
